INSTALL.txt
MANIFEST.in
README.md
setup.py
db_defaults/__init__.py
db_defaults/creator.py
db_defaults/fields.py
db_defaults/models.py
db_defaults/settings.py
db_defaults/signals.py
db_defaults/tests.py
db_defaults/db/__init__.py
db_defaults/db/generic.py
db_defaults/db/mysql.py
db_defaults/db/postgresql_psycopg2.py
django_db_defaults.egg-info/PKG-INFO
django_db_defaults.egg-info/SOURCES.txt
django_db_defaults.egg-info/dependency_links.txt
django_db_defaults.egg-info/requires.txt
django_db_defaults.egg-info/top_level.txt