Metadata-Version: 1.1
Name: django-db-defaults
Version: 0.1.1
Summary: Persist Djago model field default values to DataBase
Home-page: https://github.com/ayadav/django-db-defaults
Author: aydav
Author-email: ayadav@joshlabs.in
License: BSD
Platform: UNKNOWN
Classifier: Development Status :: 4 - Beta
Classifier: Environment :: Web Environment
Classifier: Framework :: Django
Classifier: Intended Audience :: Developers
Classifier: License :: OSI Approved :: BSD License
Classifier: Natural Language :: English
Classifier: Operating System :: OS Independent
Classifier: Programming Language :: Python
Classifier: Topic :: Utilities
